openapi_client/__init__.py
openapi_client/api_client.py
openapi_client/api_response.py
openapi_client/configuration.py
openapi_client/exceptions.py
openapi_client/py.typed
openapi_client/rest.py
openapi_client/api/__init__.py
openapi_client/api/dataset_api.py
openapi_client/api/external_apps_api.py
openapi_client/api/import_api.py
openapi_client/api/jira_functions.py
openapi_client/api/pre_conditions_api.py
openapi_client/api/project_api.py
openapi_client/api/requirement_status_api.py
openapi_client/api/test_execution_tests_api.py
openapi_client/api/test_plan_test_executions_api.py
openapi_client/api/test_plan_tests_api.py
openapi_client/api/test_repository_api.py
openapi_client/api/test_run_api.py
openapi_client/api/test_run_status_api.py
openapi_client/api/test_sets_api.py
openapi_client/api/test_step_api.py
openapi_client/api/tests_api.py
openapi_client/models/__init__.py
openapi_client/models/called_step.py
openapi_client/models/create_step.py
openapi_client/models/create_step_request_body.py
openapi_client/models/create_step_response.py
openapi_client/models/create_step_response_step.py
openapi_client/models/custom_field_meta_information.py
openapi_client/models/data_field.py
openapi_client/models/dataset_parameter.py
openapi_client/models/defects.py
openapi_client/models/error.py
openapi_client/models/field_value.py
openapi_client/models/file.py
openapi_client/models/file_response.py
openapi_client/models/folder_rest_bean.py
openapi_client/models/get_testruns200_response_inner.py
openapi_client/models/get_testruns200_response_inner_evidences_inner.py
openapi_client/models/get_testruns200_response_inner_steps_inner.py
openapi_client/models/iteration_step_information.py
openapi_client/models/model10_api_test_get200_response_inner.py
openapi_client/models/model10_api_test_get200_response_inner_definition.py
openapi_client/models/model10_api_test_get200_response_inner_definition_one_of.py
xray_combined_api-1.0.1.dist-info/METADATA
xray_combined_api-1.0.1.dist-info/WHEEL
xray_combined_api-1.0.1.dist-info/top_level.txt
xray_combined_api-1.0.1.dist-info/RECORD
