Metadata-Version: 2.1
Name: xray_combined_api
Version: 1.0.1
Summary: A combination of XRAY's REST API v1 and v2
Home-page: 
Author: 
Author-email: 
Keywords: OpenAPI,OpenAPI-Generator,Xray REST API
Requires-Dist: urllib3<3.0.0,>=1.25.3
Requires-Dist: python-dateutil>=2.8.2
Requires-Dist: pydantic>=2
Requires-Dist: typing-extensions>=4.7.1
